LICENSE.txt
MANIFEST.in
README.rst
requirements.txt
setup.py
preview_markup/__init__.py
preview_markup/cli.py
preview_markup/converter.py
preview_markup/server.py
preview_markup.egg-info/PKG-INFO
preview_markup.egg-info/SOURCES.txt
preview_markup.egg-info/dependency_links.txt
preview_markup.egg-info/entry_points.txt
preview_markup.egg-info/requires.txt
preview_markup.egg-info/top_level.txt
preview_markup/static/favicon.ico
preview_markup/static/styling.css
preview_markup/templates/preview.html